gitrelevanthistory/__init__.py
gitrelevanthistory/gitrelevanthistory.py
git_relevant_history-1.0.0.dist-info/LICENSE
git_relevant_history-1.0.0.dist-info/METADATA
git_relevant_history-1.0.0.dist-info/WHEEL
git_relevant_history-1.0.0.dist-info/entry_points.txt
git_relevant_history-1.0.0.dist-info/top_level.txt
git_relevant_history-1.0.0.dist-info/RECORD
