Metadata-Version: 2.1
Name: git-relevant-history
Version: 1.0.0
Summary: Extract subproject with just the relevant history
Home-page: https://github.com/rainlabs-eu/git-relevant-history
Author: Rainlabs
Author-email: github@rainlabs.pl
License: Apache License 2.0
Platform: UNKNOWN
Classifier: License :: OSI Approved :: Apache Software License
Classifier: Programming Language :: Python :: 3
Classifier: Programming Language :: Python :: 3.7
License-File: LICENSE
